dazzler/__init__.py
dazzler/__main__.py
dazzler/_assets.py
dazzler/_config.py
dazzler/_dazzler.py
dazzler/_reloader.py
dazzler/_renderer.py
dazzler/_server.py
dazzler/_version.py
dazzler/errors.py
dazzler/events.py
dazzler/presets.py
dazzler/assets/electron-assets.json
dazzler/assets/electron-dazzler.js
dazzler/assets/electron-loading.html
dazzler/assets/electron-package.json
dazzler/assets/index.html
dazzler/assets/index.js
dazzler/assets/meta-ts.js
dazzler/assets/meta.js
dazzler/assets/preload-electron.js
dazzler/assets/dev/assets.json
dazzler/assets/dev/dazzler_auth_56178617fc60474bcf33.js
dazzler/assets/dev/dazzler_auth_c9bc5bf705ca1cb6d7c8.css
dazzler/assets/dev/dazzler_calendar_5ca5acd2e396054a036c.css
dazzler/assets/dev/dazzler_calendar_5e71dc7c74f948be8233.js
dazzler/assets/dev/dazzler_charts_7c99821e628c449fcad8.js
dazzler/assets/dev/dazzler_commons_be1e4ad56c7c80370f7f.css
dazzler/assets/dev/dazzler_commons_c7ef17c1ba8dd592aab7.js
dazzler/assets/dev/dazzler_core_682608afbcf8ddf3d287.js
dazzler/assets/dev/dazzler_core_882925f12d29858cb901.css
dazzler/assets/dev/dazzler_extra_2f0d205c7db3c55141b3.css
dazzler/assets/dev/dazzler_extra_f51aa60332d9858554a6.js
dazzler/assets/dev/dazzler_html_45a6d152ea8f269d5203.js
dazzler/assets/dev/dazzler_icons_06f209c1c9ccc84007bd.js
dazzler/assets/dev/dazzler_markdown_3e467a81fcd98cd53982.js
dazzler/assets/dev/dazzler_renderer_9ddc83346268cd95874b.js
dazzler/assets/dev/dazzler_svg_1ed82ac004f43fac9589.js
dazzler/assets/dev/dazzler_test_6f452d79403cd7b93553.js
dazzler/assets/dev/dazzler_ts_8ca9130138f6f4c129ce.js
dazzler/assets/dist/assets.json
dazzler/assets/dist/dazzler_222_0dc8398724c1321afd9c.js
dazzler/assets/dist/dazzler_292_11a34a6b02a69902ded4.js
dazzler/assets/dist/dazzler_371_cd7172b384e7eb237902.js
dazzler/assets/dist/dazzler_991_01538ddbfeb471c96e8d.js
dazzler/assets/dist/dazzler_auth_052906d666f9101b1652.css
dazzler/assets/dist/dazzler_auth_76a996a9dea4ab195038.js
dazzler-0.10.0.dist-info/LICENSE
dazzler-0.10.0.dist-info/METADATA
dazzler-0.10.0.dist-info/WHEEL
dazzler-0.10.0.dist-info/entry_points.txt
dazzler-0.10.0.dist-info/top_level.txt
dazzler-0.10.0.dist-info/RECORD
