Metadata-Version: 2.1
Name: dazzler
Version: 0.10.0
Summary: Async Web Framework
Home-page: https://github.com/T4rk1n/dazzler
Author: Philippe Duval
Author-email: t4rk@outlook.com
License: MIT
Keywords: async,web,react,asyncio,aiohttp
Platform: UNKNOWN
Classifier: Programming Language :: Python
Classifier: Programming Language :: Python :: 3.7
Classifier: Programming Language :: Python :: 3.8
Classifier: Programming Language :: Python :: 3.9
Classifier: Topic :: Internet :: WWW/HTTP
Classifier: Topic :: Internet :: WWW/HTTP :: Session
Classifier: Topic :: Software Development :: Libraries
Classifier: Topic :: Software Development :: Libraries :: Application Frameworks
Classifier: License :: OSI Approved :: MIT License
Classifier: Intended Audience :: Developers
License-File: LICENSE
Requires-Dist: precept (==0.6.6)
Requires-Dist: aiohttp (==3.8.1)
Requires-Dist: appdirs (==1.4.4)
Requires-Dist: stringcase (==1.2.0)
Requires-Dist: itsdangerous (==2.0.1)
Provides-Extra: electron
Requires-Dist: PyInstaller (==4.7) ; extra == 'electron'
Provides-Extra: postgresql
Requires-Dist: aiopg (==1.3.3) ; extra == 'postgresql'
Provides-Extra: redis
Requires-Dist: aioredis (==1.3.1) ; extra == 'redis'
